natex/__init__.py
natex/__main__.py
natex/natex.py
natex/test.py
natex-1.0.8.dist-info/METADATA
natex-1.0.8.dist-info/WHEEL
natex-1.0.8.dist-info/top_level.txt
natex-1.0.8.dist-info/RECORD
