Metadata-Version: 2.1
Name: natex
Version: 1.0.8
Summary: Regular Expressions turbo-charged with notations for part-of-speech and dependency tree tags
Home-page: https://github.com/polygoat/natex-py
Author: Dan Borufka
Author-email: danborufka@gmail.com
License: MIT
Keywords: regex regular expression nlp pos dep
Platform: UNKNOWN
Classifier: Programming Language :: Python :: 3
Classifier: Development Status :: 3 - Alpha
Classifier: Topic :: Utilities
Classifier: License :: OSI Approved :: MIT License
Classifier: Operating System :: OS Independent
Requires-Python: >=3.6
Requires-Dist: pydash
Requires-Dist: stanza
